bookmind/__init__.py
bookmind-0.0.0.dist-info/METADATA
bookmind-0.0.0.dist-info/WHEEL
bookmind-0.0.0.dist-info/RECORD
