Metadata-Version: 2.1
Name: bookmind
Version: 0.0.0
Summary: Conversing with Books.
License: Apache-2.0
Author: zhangshulin
Author-email: zhangsl@yeah.net
Requires-Python: >=3.8,<4
Classifier: License :: OSI Approved :: Apache Software License
Classifier: Programming Language :: Python :: 3
Classifier: Programming Language :: Python :: 3.8
Classifier: Programming Language :: Python :: 3.9
Classifier: Programming Language :: Python :: 3.10
Classifier: Programming Language :: Python :: 3.11
Classifier: Programming Language :: Python :: 3.12
Classifier: Programming Language :: Python :: 3.13
